makolator-2.13.0.dist-info/METADATA
makolator-2.13.0.dist-info/WHEEL
makolator-2.13.0.dist-info/entry_points.txt
makolator-2.13.0.dist-info/licenses/LICENSE
makolator/__init__.py
makolator/__main__.py
makolator/_inplace.py
makolator/_staticcode.py
makolator/_util.py
makolator/cli.py
makolator/config.py
makolator/datamodel.py
makolator/escape.py
makolator/exceptions.py
makolator/helper.py
makolator/info.py
makolator/makolator.py
makolator/tags.py
makolator/tracker.py
makolator-2.13.0.dist-info/RECORD
