Metadata-Version: 2.1
Name: makolator
Version: 2.13.0
Summary: Extended Mako Templates for Python
Classifier: Programming Language :: Python :: 3
Classifier: Operating System :: OS Independent
Project-URL: Homepage, https://github.com/nbiotcloud/makolator
Project-URL: Documentation, https://makolator.readthedocs.io/en/stable/
Project-URL: Bug Tracker, https://github.com/nbiotcloud/makolator/issues
Requires-Python: <4.0,>=3.10.0
Requires-Dist: aligntext>=1.0.3
Requires-Dist: attrs>=23.1.0
Requires-Dist: mako>=1.3.9
Requires-Dist: outputfile>=1.3.2
Requires-Dist: uniquer>=1.0.5
